bgmhan/__init__.py
bgmhan/data_processor.py
bgmhan/models.py
bgmhan/pipeline.py
bgmhan-0.1.0.dist-info/LICENSE
bgmhan-0.1.0.dist-info/METADATA
bgmhan-0.1.0.dist-info/WHEEL
bgmhan-0.1.0.dist-info/top_level.txt
bgmhan-0.1.0.dist-info/RECORD
